passagemath_latte_4ti2/__init__.py
passagemath_latte_4ti2.libs/lib4ti2gmp-e5fe33a0.so.0.0.0
passagemath_latte_4ti2.libs/lib4ti2int32-4e12cf2e.so.0.0.0
passagemath_latte_4ti2.libs/lib4ti2int64-db1953b3.so.0.0.0
passagemath_latte_4ti2.libs/lib4ti2util-d6fbe88e.so.0.0.0
passagemath_latte_4ti2.libs/libLiDIA-243b8d67.so.0.0.0
passagemath_latte_4ti2.libs/libcddgmp-ecb88865.so.0.1.3
passagemath_latte_4ti2.libs/libgcc_s-2d945d6c.so.1
passagemath_latte_4ti2.libs/libgf2x-e54d5509.so.3.0.0
passagemath_latte_4ti2.libs/libglpk-b001aa75.so.40.3.1
passagemath_latte_4ti2.libs/libgmp-28992bcb.so.10.5.0
passagemath_latte_4ti2.libs/libgmpxx-fecb01a9.so.4.7.0
passagemath_latte_4ti2.libs/liblatte-6a7c0993.so.0.0.0
passagemath_latte_4ti2.libs/libnormalize-679f2a74.so.0.0.0
passagemath_latte_4ti2.libs/libntl-21cb123c.so.45.0.0
passagemath_latte_4ti2.libs/libstdc++-85f2cd6d.so.6.0.33
passagemath_latte_4ti2.libs/libzsolve-2150eeb0.so.0.0.0
sage/all__sagemath_latte_4ti2.py
sage/interfaces/all__sagemath_latte_4ti2.py
sage/interfaces/four_ti_2.py
sage/interfaces/latte.py
sage/libs/all__sagemath_latte_4ti2.py
sage/libs/latte_int.cpython-314t-aarch64-linux-musl.so
sage/libs/latte_int.pyx
sage_wheels/bin/4ti2gmp
sage_wheels/bin/4ti2int32
sage_wheels/bin/4ti2int64
sage_wheels/bin/ConvertCDDextToLatte
sage_wheels/bin/ConvertCDDineToLatte
sage_wheels/bin/circuits
sage_wheels/bin/count
sage_wheels/bin/count-linear-forms-from-polynomial
sage_wheels/bin/ehrhart
sage_wheels/bin/ehrhart3
sage_wheels/bin/genmodel
sage_wheels/bin/gensymm
sage_wheels/bin/graver
sage_wheels/bin/groebner
sage_wheels/bin/hilbert
sage_wheels/bin/hilbert-from-rays
sage_wheels/bin/hilbert-from-rays-symm
sage_wheels/bin/integrate
sage_wheels/bin/latte-maximize
sage_wheels/bin/latte-minimize
sage_wheels/bin/latte2ext
sage_wheels/bin/latte2ine
sage_wheels/bin/markov
sage_wheels/bin/minimize
sage_wheels/bin/normalform
sage_wheels/bin/output
sage_wheels/bin/polyhedron-to-cones
passagemath_latte_4ti2-10.6.43.dist-info/METADATA
passagemath_latte_4ti2-10.6.43.dist-info/WHEEL
passagemath_latte_4ti2-10.6.43.dist-info/top_level.txt
passagemath_latte_4ti2-10.6.43.dist-info/RECORD
